cyclosible-0.1.dist-info/METADATA
cyclosible-0.1.dist-info/top_level.txt
cyclosible-0.1.dist-info/DESCRIPTION.rst
cyclosible-0.1.dist-info/entry_points.txt
cyclosible-0.1.dist-info/RECORD
cyclosible-0.1.dist-info/metadata.json
cyclosible-0.1.dist-info/WHEEL
cyclosible/__init__.py
cyclosible/manage.py
cyclosible/playbook/tests.py
cyclosible/playbook/urls.py
cyclosible/playbook/serializers.py
cyclosible/playbook/tasks.py
cyclosible/playbook/models.py
cyclosible/playbook/__init__.py
cyclosible/playbook/views.py
cyclosible/playbook/callbacks_ansiblev1.py
cyclosible/playbook/permissions.py
cyclosible/playbook/admin.py
cyclosible/playbook/plugins/__init__.py
cyclosible/playbook/plugins/storage/base.py
cyclosible/playbook/plugins/storage/s3.py
cyclosible/playbook/plugins/storage/__init__.py
cyclosible/playbook/__pycache__/__init__.cpython-34.pyc
cyclosible/playbook/__pycache__/models.cpython-34.pyc
cyclosible/playbook/__pycache__/admin.cpython-34.pyc
cyclosible/playbook/migrations/0003_auto_20151028_1735.py
cyclosible/playbook/migrations/0002_auto_20151028_1653.py
cyclosible/playbook/migrations/0004_playbookrunhistory_log_url.py
cyclosible/playbook/migrations/__init__.py
cyclosible/playbook/migrations/0001_initial.py
cyclosible/playbook/migrations/__pycache__/0002_auto_20151028_1653.cpython-34.pyc
cyclosible/playbook/migrations/__pycache__/0001_initial.cpython-34.pyc
cyclosible/playbook/migrations/__pycache__/__init__.cpython-34.pyc
cyclosible/playbook/migrations/__pycache__/0003_auto_20151028_1735.cpython-34.pyc
cyclosible/playbook/migrations/__pycache__/0004_playbookrunhistory_log_url.cpython-34.pyc
cyclosible/__pycache__/__init__.cpython-34.pyc
cyclosible/Cyclosible/urls.py
cyclosible/Cyclosible/serializers.py
cyclosible/Cyclosible/routers.py
cyclosible/Cyclosible/settings.py
cyclosible/Cyclosible/celery.py
cyclosible/Cyclosible/__init__.py
cyclosible/Cyclosible/wsgi.py
cyclosible/Cyclosible/views.py
cyclosible/Cyclosible/websocket.py
cyclosible/Cyclosible/__pycache__/wsgi.cpython-34.pyc
cyclosible/Cyclosible/__pycache__/__init__.cpython-34.pyc
cyclosible/Cyclosible/__pycache__/settings.cpython-34.pyc
cyclosible/Cyclosible/__pycache__/celery.cpython-34.pyc
