Metadata-Version: 2.0
Name: cyclosible
Version: 0.1
Summary: Cyclosible is a web-api to manage ansible
Home-page: http://www.cycloid.io/cyclosible
Author: Cycloid
Author-email: julien.syx@cycloid.io
License: Apache
Platform: UNKNOWN
Classifier: Environment :: Console
Classifier: Intended Audience :: Information Technology
Classifier: Intended Audience :: System Administrators
Classifier: License :: OSI Approved :: Apache Software License
Classifier: Operating System :: POSIX :: Linux
Classifier: Programming Language :: Python
Classifier: Programming Language :: Python :: 2
Classifier: Programming Language :: Python :: 2.7
Classifier: Programming Language :: Python :: 3
Classifier: Programming Language :: Python :: 3.3
Classifier: Programming Language :: Python :: 3.4
Requires-Dist: djangorestframework
Requires-Dist: django (>=1.8)
Requires-Dist: mysqlclient
Requires-Dist: django-rest-swagger
Requires-Dist: colorlog
Requires-Dist: ansible
Requires-Dist: PyYAML
Requires-Dist: django-celery
Requires-Dist: markdown
Requires-Dist: django-guardian
Requires-Dist: django-filter
Requires-Dist: boto
Requires-Dist: redis
Requires-Dist: django-websocket-redis
Requires-Dist: stevedore
